LICENSE
MANIFEST.in
README.md
setup.cfg
setup.py
tap_recurly/__init__.py
tap_recurly/context.py
tap_recurly/discover.py
tap_recurly/recurly.py
tap_recurly/streams.py
tap_recurly/sync.py
tap_recurly.egg-info/PKG-INFO
tap_recurly.egg-info/SOURCES.txt
tap_recurly.egg-info/dependency_links.txt
tap_recurly.egg-info/entry_points.txt
tap_recurly.egg-info/requires.txt
tap_recurly.egg-info/top_level.txt
tap_recurly/schemas/accounts.json
tap_recurly/schemas/adjustments.json
tap_recurly/schemas/billing_info.json
tap_recurly/schemas/coupon_redemptions.json
tap_recurly/schemas/coupons.json
tap_recurly/schemas/invoices.json
tap_recurly/schemas/plans.json
tap_recurly/schemas/plans_add_ons.json
tap_recurly/schemas/schema-fixtures.json
tap_recurly/schemas/subscriptions.json
tap_recurly/schemas/transactions.json