Metadata-Version: 2.1
Name: tap-recurly
Version: 0.0.3
Summary: Singer.io tap for extracting data from the Recurly API
Home-page: http://github.com/singer-io/tap-recurly
Author: Stitch
License: UNKNOWN
Platform: UNKNOWN
Classifier: Programming Language :: Python :: 3 :: Only
Provides-Extra: dev
